doc_inherit/__init__.py
doc_inherit/decorators.py
doc_inherit/metaclasses.py
python_doc_inherit-0.3.0.dist-info/DESCRIPTION.rst
python_doc_inherit-0.3.0.dist-info/METADATA
python_doc_inherit-0.3.0.dist-info/RECORD
python_doc_inherit-0.3.0.dist-info/WHEEL
python_doc_inherit-0.3.0.dist-info/metadata.json
python_doc_inherit-0.3.0.dist-info/top_level.txt
