Metadata-Version: 2.0
Name: python-doc-inherit
Version: 0.3.0
Summary: Utilities to inherit method documentation from parent classes.
Home-page: https://github.com/kavdev/python-doc-inherit/
Author: Alexander Kavanaugh
Author-email: alex@kavdev.io
License: License :: OSI Approved :: MIT License
Keywords: doc_inherit doc inherit
Platform: UNKNOWN
Classifier: Development Status :: 4 - Beta
Classifier: Intended Audience :: Developers
Classifier: License :: OSI Approved :: MIT License
Classifier: Natural Language :: English
Classifier: Programming Language :: Python :: 2.7
Classifier: Programming Language :: Python :: 3.4
Classifier: Programming Language :: Python :: 3.5
